app/__init__.py
app/main.py
app/utils.py
cadprox-5.6.dist-info/LICENSE
cadprox-5.6.dist-info/METADATA
cadprox-5.6.dist-info/WHEEL
cadprox-5.6.dist-info/entry_points.txt
cadprox-5.6.dist-info/top_level.txt
cadprox-5.6.dist-info/RECORD
