Metadata-Version: 2.1
Name: cadprox
Version: 5.6
Summary: A tool to manage Caddy reverse proxy configurations with Cloudflare DNS.
Home-page: https://github.com/reegen66/cadprox
Author: Piotr Tamu (Thriveroute.com)
Author-email: nonyour@ssenisub.com
Classifier: Programming Language :: Python :: 3
Classifier: License :: OSI Approved :: MIT License
Classifier: Operating System :: OS Independent
Requires-Python: >=3.11
License-File: LICENSE
Requires-Dist: requests
Requires-Dist: dnspython
Requires-Dist: boto3
Requires-Dist: python-dotenv
